MANIFEST.in
README.rst
RELEASE-VERSION
setup.cfg
setup.py
bin/relint
bin/reschema-doc
examples/bookstore.json
examples/bookstore.yaml
examples/yaml_to_json.py
gitpy_versioning/__init__.py
gitpy_versioning/test_gitpy_versioning.py
reschema/__init__.py
reschema/doc.py
reschema/exceptions.py
reschema/html.py
reschema/json_loader.py
reschema/jsonmergepatch.py
reschema/jsonschema.py
reschema/lint.py
reschema/loader_nodes.py
reschema/parser.py
reschema/reljsonpointer.py
reschema/servicedef.css
reschema/servicedef.js
reschema/servicedef.py
reschema/settings.py
reschema/tohtml.py
reschema/util.py
reschema/yaml_loader.py
reschema.egg-info/PKG-INFO
reschema.egg-info/SOURCES.txt
reschema.egg-info/dependency_links.txt
reschema.egg-info/requires.txt
reschema.egg-info/top_level.txt
test/test_convert_2_1.py
test/test_entity.py
test/test_lint.py
test/test_marked_load.py
test/test_parser.py
test/test_reschema.py
test/test_reschema_doc.py