Metadata-Version: 2.1
Name: reschema
Version: 2.0
Summary: reschema - Parse REST API service defintions into Python objects, support documentation generation
Home-page: http://pythonhosted.org/steelscript
Author: Riverbed Technology
Author-email: eng-github@riverbed.com
License: MIT
Keywords: reschema
Platform: Linux
Platform: Mac OS
Platform: Windows
Classifier: Development Status :: 4 - Beta
Classifier: Intended Audience :: Developers
Classifier: License :: OSI Approved :: MIT License
Classifier: Programming Language :: Python :: 3.5
Classifier: Topic :: Software Development :: Documentation
Requires-Python: >3.5.0
Provides-Extra: dev
Provides-Extra: all
Provides-Extra: test
Provides-Extra: doc
